source_github/__init__.py
source_github/backoff_strategies.py
source_github/config_migrations.py
source_github/constants.py
source_github/errors_handlers.py
source_github/github_schema.py
source_github/graphql.py
source_github/run.py
source_github/schemas/assignees.json
source_github/schemas/branches.json
source_github/schemas/collaborators.json
source_github/schemas/comments.json
source_github/schemas/commit_comment_reactions.json
source_github/schemas/commit_comments.json
source_github/schemas/commits.json
source_github/schemas/contributor_activity.json
source_github/schemas/deployments.json
source_github/schemas/events.json
source_github/schemas/issue_comment_reactions.json
source_github/schemas/issue_events.json
source_github/schemas/issue_labels.json
source_github/schemas/issue_milestones.json
source_github/schemas/issue_reactions.json
source_github/schemas/issue_timeline_events.json
source_github/schemas/issues.json
source_github/schemas/organizations.json
source_github/schemas/project_cards.json
source_github/schemas/project_columns.json
source_github/schemas/projects.json
source_github/schemas/projects_v2.json
source_github/schemas/pull_request_comment_reactions.json
source_github/schemas/pull_request_commits.json
source_github/schemas/pull_request_stats.json
source_github/schemas/pull_requests.json
source_github/schemas/releases.json
source_github/schemas/repositories.json
source_github/schemas/review_comments.json
source_github/schemas/reviews.json
source_github/schemas/shared/events/comment.json
source_github/schemas/shared/events/commented.json
source_github/schemas/shared/events/committed.json
source_github/schemas/shared/events/cross_referenced.json
source_github/schemas/shared/events/reviewed.json
source_github/schemas/shared/reaction.json
source_github/schemas/shared/reactions.json
source_github/schemas/shared/user.json
source_github/schemas/shared/user_graphql.json
source_github/schemas/stargazers.json
source_github/schemas/tags.json
airbyte_source_github-2.1.8.dist-info/METADATA
airbyte_source_github-2.1.8.dist-info/WHEEL
airbyte_source_github-2.1.8.dist-info/entry_points.txt
airbyte_source_github-2.1.8.dist-info/RECORD
