Metadata-Version: 2.1
Name: airbyte-source-github
Version: 2.1.8
Summary: Source implementation for GitHub.
Home-page: https://airbyte.com
License: ELv2
Author: Airbyte
Author-email: contact@airbyte.io
Requires-Python: >=3.10,<3.14
Classifier: License :: Other/Proprietary License
Classifier: Programming Language :: Python :: 3
Classifier: Programming Language :: Python :: 3.10
Classifier: Programming Language :: Python :: 3.11
Classifier: Programming Language :: Python :: 3.12
Classifier: Programming Language :: Python :: 3.13
Requires-Dist: airbyte-cdk (>=7.4.1,<8.0.0)
Requires-Dist: sgqlc (==16.3)
Project-URL: Documentation, https://docs.airbyte.com/integrations/sources/github
Project-URL: Repository, https://github.com/airbytehq/airbyte
